file_cycle.py
file_cycle-0.0.2.dist-info/LICENSE
file_cycle-0.0.2.dist-info/METADATA
file_cycle-0.0.2.dist-info/WHEEL
file_cycle-0.0.2.dist-info/top_level.txt
file_cycle-0.0.2.dist-info/RECORD
